walkdir.py
walkdir-0.4.1.dist-info/DESCRIPTION.rst
walkdir-0.4.1.dist-info/METADATA
walkdir-0.4.1.dist-info/RECORD
walkdir-0.4.1.dist-info/WHEEL
walkdir-0.4.1.dist-info/metadata.json
walkdir-0.4.1.dist-info/top_level.txt
