Metadata-Version: 2.0
Name: walkdir
Version: 0.4.1
Summary: Tools to manipulate and filter os.walk() style iteration
Home-page: http://walkdir.readthedocs.org
Author: Nick Coghlan
Author-email: ncoghlan@gmail.com
License: Simplified BSD License
Platform: UNKNOWN
Classifier: Development Status :: 5 - Production/Stable
Classifier: License :: OSI Approved :: BSD License
Classifier: Programming Language :: Python :: 2
Classifier: Programming Language :: Python :: 2.6
Classifier: Programming Language :: Python :: 2.7
Classifier: Programming Language :: Python :: 3
Classifier: Programming Language :: Python :: 3.3
Classifier: Programming Language :: Python :: 3.4
Classifier: Programming Language :: Python :: 3.5
